qupled/__init__.py
qupled/classic.py
qupled/quantum.py
qupled/util.py
qupled/Darwin/qupled.so
qupled_test-0.0.1.dist-info/METADATA
qupled_test-0.0.1.dist-info/WHEEL
qupled_test-0.0.1.dist-info/top_level.txt
qupled_test-0.0.1.dist-info/RECORD
